<act id='3b868b69-3bc4-4066-aa27-1387aeab73df' congress='64' statutes-at-large-volume='39' date='1916-05-04' sequence='3606' insertion='AAAA' format='2' search-key='1916-05-04:109' print-in-supplement='false' include-in-online-release-point='true'>
 <num>109</num>
 <public-law>68</public-law>
 <record id='6bf1db67-d31c-480a-88d0-a02a04279f76' sequence='0' usckey='4500000000006300000000000000000000'>
  <act-section>1</act-section>
  <statutes-at-large-page>61</statutes-at-large-page>
  <united-states-code-title>45</united-states-code-title>
  <united-states-code-section>63</united-states-code-section>
  <united-states-code-status>Rep.</united-states-code-status>
 </record>
</act>