<act id='4fad3a3f-e6cd-4e04-9de1-2494956b8ef6' congress='88' statutes-at-large-volume='78' date='1964-05-26' sequence='13081' insertion='AAAA' format='3' search-key='88-310' print-in-supplement='false' include-in-online-release-point='true'>
 <num>88-310</num>
 <record id='5fac69b5-0826-467d-b1fd-7396fa3a5c48' sequence='0' usckey='2200000000028400000000000e00000000'>
  <act-section>1, 2</act-section>
  <statutes-at-large-page>200</statutes-at-large-page>
  <united-states-code-title>22</united-states-code-title>
  <united-states-code-section>284e</united-states-code-section>
 </record>
</act>