<act id='150a806f-507e-41b4-9269-82ca334ac4ff' congress='75' statutes-at-large-volume='50' date='1937-08-20' sequence='6450' insertion='AAAA' format='2' search-key='1937-08-20:716' print-in-supplement='false' include-in-online-release-point='true'>
 <num>716</num>
 <public-law>325</public-law>
 <record id='9ead8102-3a77-410e-a443-856f1a099f3f' sequence='0' usckey='1000000000152200000000000000000000'>
  <act-section>1, 2</act-section>
  <statutes-at-large-page>724</statutes-at-large-page>
  <united-states-code-title>10</united-states-code-title>
  <united-states-code-section>1522, 1542</united-states-code-section>
  <united-states-code-status>Rev. T.</united-states-code-status>
 </record>
</act>