<act id='2bfc3c20-6d94-4170-a17b-8c76e8cfa861' congress='97' statutes-at-large-volume='96' date='1982-10-15' sequence='17289' insertion='AAAA' format='3' search-key='97-331' print-in-supplement='false' include-in-online-release-point='true'>
 <num>97-331</num>
 <record id='fdd0e0eb-b765-4dea-8b2d-a81423c79cda' sequence='0' usckey='1500000000138100000000000000000000nt'>
  <act-section>1</act-section>
  <statutes-at-large-page>1619</statutes-at-large-page>
  <united-states-code-title>15</united-states-code-title>
  <united-states-code-section>1381 nt</united-states-code-section>
  <united-states-code-status>Rep.</united-states-code-status>
 </record>
 <record id='58164896-ac64-4c68-8bb5-aad1a9be5c0f' sequence='1' usckey='1500000000140900000000000000000000'>
  <act-section>2(a)-(d)</act-section>
  <statutes-at-large-page>1619</statutes-at-large-page>
  <united-states-code-title>15</united-states-code-title>
  <united-states-code-section>1409, 1921, 1949, 1990g</united-states-code-section>
  <united-states-code-status>Rep.</united-states-code-status>
 </record>
 <record id='53dca89c-99ba-4c49-88f8-1fee73e96e70' sequence='2' usckey='1500000000139200000000000000000000'>
  <act-section>3</act-section>
  <statutes-at-large-page>1619</statutes-at-large-page>
  <united-states-code-title>15</united-states-code-title>
  <united-states-code-section>1392</united-states-code-section>
  <united-states-code-status>Rep.</united-states-code-status>
 </record>
 <record id='2fae911c-eba4-44cd-b707-690333babb2e' sequence='3' usckey='1500000000141800000000000000000000'>
  <act-section>4(a)</act-section>
  <statutes-at-large-page>1619</statutes-at-large-page>
  <united-states-code-title>15</united-states-code-title>
  <united-states-code-section>1418</united-states-code-section>
  <united-states-code-status>Rep.</united-states-code-status>
 </record>
 <record id='14ec297e-0bc4-4ce3-9f3b-e9ea1afe89fe' sequence='4' usckey='1500000000141300000000000000000000'>
  <act-section>4(b)</act-section>
  <statutes-at-large-page>1620</statutes-at-large-page>
  <united-states-code-title>15</united-states-code-title>
  <united-states-code-section>1413</united-states-code-section>
  <united-states-code-status>Rep.</united-states-code-status>
 </record>
</act>