<act id='06c38d2d-1d6f-4013-865b-043a8a8fdd09' congress='57' statutes-at-large-volume='32' date='1902-12-23' sequence='2776' insertion='AAAA' format='2' search-key='1902-12-23:13' print-in-supplement='false' include-in-online-release-point='true'>
 <num>13</num>
 <public-law>11</public-law>
 <record id='73aa9a1b-2243-498f-8b47-ae7713dd35b3' sequence='0' usckey='3800000000011300000000000000000000nt'>
  <statutes-at-large-page>761</statutes-at-large-page>
  <united-states-code-title>38</united-states-code-title>
  <united-states-code-section>113 nt</united-states-code-section>
  <united-states-code-status>Rev. T.</united-states-code-status>
 </record>
</act>