<act id='3bb26c3f-037a-4e2d-9832-42ead7170d39' congress='95' statutes-at-large-volume='92' date='1978-11-08' sequence='16612' insertion='AAAA' format='3' search-key='95-606' print-in-supplement='false' include-in-online-release-point='true'>
 <num>95-606</num>
 <record id='504e366e-8e0d-47a0-afd0-57aa79f2e455' sequence='0' usckey='3600000000037100000000000000000000nt'>
  <statutes-at-large-page>3045</statutes-at-large-page>
  <united-states-code-title>36</united-states-code-title>
  <united-states-code-section>371 nt</united-states-code-section>
  <united-states-code-status>Rep.</united-states-code-status>
 </record>
 <record id='69a94d15-8ee0-4ff3-a676-e0782fa65f63' sequence='1' usckey='3600000000037100000000000000000000'>
  <act-section>1(a)</act-section>
  <statutes-at-large-page>3045</statutes-at-large-page>
  <united-states-code-title>36</united-states-code-title>
  <united-states-code-section>371</united-states-code-section>
  <united-states-code-status>Rev. T.</united-states-code-status>
 </record>
 <record id='e2ce475d-4032-4329-afee-80435668af3c' sequence='2' usckey='360000000003720000000000000382000b'>
  <act-section>1(b)</act-section>
  <statutes-at-large-page>3045</statutes-at-large-page>
  <united-states-code-title>36</united-states-code-title>
  <united-states-code-section>372-382b</united-states-code-section>
  <united-states-code-status>Rev. T.</united-states-code-status>
 </record>
 <record id='41121d01-7896-49a4-a954-4bed3bf032ae' sequence='3' usckey='3600000000039100000000000003960000'>
  <act-section>2</act-section>
  <statutes-at-large-page>3050</statutes-at-large-page>
  <united-states-code-title>36</united-states-code-title>
  <united-states-code-section>391-396</united-states-code-section>
  <united-states-code-status>Rev. T.</united-states-code-status>
 </record>
</act>