<act id='d5fd3a98-e787-41da-9e76-f5781a84caaf' congress='87' statutes-at-large-volume='75' date='1961-08-07' sequence='12394' insertion='AAAA' format='3' search-key='87-126' print-in-supplement='false' include-in-online-release-point='true'>
 <num>87-126</num>
 <record id='aae03ed7-8526-4657-b7da-8954827dfa41' sequence='0' usckey='1600000000045900000000000b00000000'>
  <act-section>1</act-section>
  <statutes-at-large-page>284</statutes-at-large-page>
  <united-states-code-title>16</united-states-code-title>
  <united-states-code-section>459b</united-states-code-section>
 </record>
 <record id='c736ac25-b0c1-4824-a5f0-c2e2f0053cdf' sequence='1' usckey='1600000000045900000000000b00010000'>
  <act-section>2</act-section>
  <statutes-at-large-page>287</statutes-at-large-page>
  <united-states-code-title>16</united-states-code-title>
  <united-states-code-section>459b-1</united-states-code-section>
 </record>
 <record id='41d50913-b6ec-4d78-9884-bf68e2a3ded6' sequence='2' usckey='1600000000045900000000000b00020000'>
  <act-section>3</act-section>
  <statutes-at-large-page>288</statutes-at-large-page>
  <united-states-code-title>16</united-states-code-title>
  <united-states-code-section>459b-2</united-states-code-section>
 </record>
 <record id='05735ec8-3fd9-469e-ad2a-9a75cbc64e90' sequence='3' usckey='1600000000045900000000000b00030000'>
  <act-section>4</act-section>
  <statutes-at-large-page>288</statutes-at-large-page>
  <united-states-code-title>16</united-states-code-title>
  <united-states-code-section>459b-3</united-states-code-section>
 </record>
 <record id='ce87dc6d-f921-49e7-bafc-d5a0d3b075ce' sequence='4' usckey='1600000000045900000000000b00040000'>
  <act-section>5</act-section>
  <statutes-at-large-page>290</statutes-at-large-page>
  <united-states-code-title>16</united-states-code-title>
  <united-states-code-section>459b-4</united-states-code-section>
 </record>
 <record id='00c4a93b-2136-4955-8256-f875e030fd6a' sequence='5' usckey='1600000000045900000000000b00050000'>
  <act-section>6</act-section>
  <statutes-at-large-page>291</statutes-at-large-page>
  <united-states-code-title>16</united-states-code-title>
  <united-states-code-section>459b-5</united-states-code-section>
 </record>
 <record id='e33a6cd4-05da-41a9-b3e2-88af32aafa49' sequence='6' usckey='1600000000045900000000000b00060000'>
  <act-section>7</act-section>
  <statutes-at-large-page>291</statutes-at-large-page>
  <united-states-code-title>16</united-states-code-title>
  <united-states-code-section>459b-6</united-states-code-section>
 </record>
 <record id='141b649d-dacf-47c0-bac8-0eec30e5c203' sequence='7' usckey='1600000000045900000000000b00070000'>
  <act-section>8</act-section>
  <statutes-at-large-page>292</statutes-at-large-page>
  <united-states-code-title>16</united-states-code-title>
  <united-states-code-section>459b-7</united-states-code-section>
  <united-states-code-status>Elim.</united-states-code-status>
 </record>
 <record id='89bea162-b025-454d-b34f-cc41cb61eba8' sequence='8' usckey='1600000000045900000000000b00080000'>
  <act-section>9</act-section>
  <statutes-at-large-page>293</statutes-at-large-page>
  <united-states-code-title>16</united-states-code-title>
  <united-states-code-section>459b-8</united-states-code-section>
 </record>
 <record id='fed4bea3-fa4c-4089-89a3-66e8fce1d01b' sequence='9' usckey='1600000000045900000000000b00000000nt'>
  <act-section>10</act-section>
  <statutes-at-large-page>293</statutes-at-large-page>
  <united-states-code-title>16</united-states-code-title>
  <united-states-code-section>459b nt</united-states-code-section>
 </record>
</act>