<act id='31725455-5467-4a75-906a-62ceeaac038b' congress='100' statutes-at-large-volume='101' date='1987-07-11' sequence='18056' insertion='AAAA' format='3' search-key='100-72' print-in-supplement='false' include-in-online-release-point='true'>
 <num>100-72</num>
 <record id='3bc49092-63bf-4626-aec3-dc24f87e81dd' sequence='0' usckey='1500000000063100000000000000000000nt'>
  <act-section>1</act-section>
  <statutes-at-large-page>477</statutes-at-large-page>
  <united-states-code-title>15</united-states-code-title>
  <united-states-code-section>631 nt</united-states-code-section>
 </record>
 <record id='45b030f2-69e5-453d-aa00-80c7ce10787e' sequence='1' usckey='1500000000069700000000000a00000000'>
  <act-section>2</act-section>
  <statutes-at-large-page>477</statutes-at-large-page>
  <united-states-code-title>15</united-states-code-title>
  <united-states-code-section>697a</united-states-code-section>
 </record>
</act>